{
  "volume": 14,
  "total_words_audited": 273824,
  "total_anomalies_count": 75,
  "anomalies": {
    "Hyphenation Anomalies": [
      {
        "target": "law-maker",
        "description": "Splittable word (rejoins to valid word 'lawmaker')",
        "chapter": "Chapter 5 - Obscurity of God, Etc.",
        "contexts": [
          "... know of. He proceeds: \u2014 4. \"If Christ be not our law-maker and director of doing well, as well as our Redeem ...",
          "... ts or Presbyterians teach that \"Christ is not our law-maker and director of doing well,\" etc.? I dare say he ..."
        ]
      },
      {
        "target": "open-hearted",
        "description": "Splittable word (rejoins to valid word 'openhearted')",
        "chapter": "Chapter 7 - Use of Reason.",
        "contexts": [
          "... men into a good humor, and, knowing them free and open-hearted, he plies them whilst they are warm. We have ind ..."
        ]
      },
      {
        "target": "a-work",
        "description": "Splittable word (rejoins to valid word 'awork')",
        "chapter": "Chapter 9 - Protestant Pleas.",
        "contexts": [
          "... efense against the Presbyterians. He that set him a-work may pay him his wages. Protestants only tell him ..."
        ]
      },
      {
        "target": "Ro-manists",
        "description": "Capitalized hyphenation with unrecognized right particle",
        "chapter": "Chapter 13 - Popish Contradictions.",
        "contexts": [
          "... that no trouble ever was raised amongst us by the Ro-manists, here, at unawares, he informs us that his own gr ..."
        ]
      },
      {
        "target": "top-gallant",
        "description": "Splittable word (rejoins to valid word 'topgallant')",
        "chapter": "Chapter 13 - Popish Contradictions.",
        "contexts": [
          "... uiet life; another, that they carry their top and top-gallant so high, that they will go to heaven without Chri ..."
        ]
      },
      {
        "target": "sanc-tiffed",
        "description": "Hyphenated word with unrecognized particles on both sides",
        "chapter": "Chapter 17 - Latin Service.",
        "contexts": [
          "... t make it common.\" To what end, I pray, hath God sanc-tiffed it? Is it that it may be laid up and be hid from ..."
        ]
      },
      {
        "target": "Syro-Chaldean",
        "description": "Capitalized hyphenation with unrecognized left particle",
        "chapter": "Chapter 17 - Latin Service.",
        "contexts": [
          "... eir people, who began to take in a mixture of the Syro-Chaldean language with their own, the Targums were found ..."
        ]
      },
      {
        "target": "far-fetched",
        "description": "Splittable word (rejoins to valid word 'farfetched')",
        "chapter": "Chapter 18 - Communion.",
        "contexts": [
          "... it doth seem plainly to do; for, setting aside a far-fetched false notion or two about Melchizedek, and the do ..."
        ]
      },
      {
        "target": "bed-staff",
        "description": "Splittable word (rejoins to valid word 'bedstaff')",
        "chapter": "Chapter 18 - Communion.",
        "contexts": [
          "... let such things as these down our throats, but a bed-staff, to cram them down, or they will choke us in the ..."
        ]
      },
      {
        "target": "non-necessity",
        "description": "Splittable word (rejoins to valid word 'nonnecessity')",
        "chapter": "Chapter 18 - Communion.",
        "contexts": [
          "... emises, to erect his triumphant conclusion of the non-necessity of participation of the blessed cup by the people ..."
        ]
      },
      {
        "target": "Peace-making",
        "description": "Splittable word (rejoins to valid word 'Peacemaking')",
        "chapter": "Chapter 21 - Pope.",
        "contexts": [
          "... e series of men going under that name. Instead of Peace-making and reconciliation, they tell us of fierce and cr ..."
        ]
      },
      {
        "target": "inno-cency",
        "description": "Splittable word (rejoins to valid word 'innocency')",
        "chapter": "Chapter 21 - Pope.",
        "contexts": [
          "... eter: and whether he hath been such a defender of inno-cency and innocents, the day wherein God shall make inq ..."
        ]
      },
      {
        "target": "after-game",
        "description": "Splittable word (rejoins to valid word 'aftergame')",
        "chapter": "Chapter 21 - Pope.",
        "contexts": [
          "... desired, though they were many of them wise at an after-game, and turned their remoteness from them into their ..."
        ]
      },
      {
        "target": "Christian-like",
        "description": "Splittable word (rejoins to valid word 'Christianlike')",
        "chapter": "Chapter 1.",
        "contexts": [
          "... l submit; and, therefore, that it is rational and Christian-like to leave these endless contentions, and resign ou ..."
        ]
      },
      {
        "target": "pre-emi",
        "description": "Hyphenated word with unrecognized particles on both sides",
        "chapter": "Chapter 3.",
        "contexts": [
          "... aftertimes, to obviate those towering thoughts of pre-emi-nency which he foresaw that some men from externa ...",
          "... came unto us from Rome, you expressly adjudge the pre-eminence over us unto Rome, and determine that her we ..."
        ]
      },
      {
        "target": "Con-stantinop",
        "description": "Capitalized hyphenation with unrecognized right particle",
        "chapter": "Chapter 4.",
        "contexts": [
          "... oncil. Antioch. can. 13 and 15, anno 341; Concil. Con-stantinop. can. 2, anno 381. But this canon of the Nicene ..."
        ]
      },
      {
        "target": "irra-diatonis",
        "description": "Hyphenated word with unrecognized particles on both sides",
        "chapter": "Chapter 7.",
        "contexts": [
          "... us; id est, inspiratio facta divinitus et divinee irra-diatonis influxus certus.\" \"But whence are we persuaded th ..."
        ]
      },
      {
        "target": "fore-named",
        "description": "Splittable word (rejoins to valid word 'forenamed')",
        "chapter": "Chapter 7.",
        "contexts": [
          "... stionable. You may at your leisure, besides those fore-named, consult Psalm 19:8; Isaiah 8:20; Ezekiel 36:27; ..."
        ]
      },
      {
        "target": "wire-draw",
        "description": "Splittable word (rejoins to valid word 'wiredraw')",
        "chapter": "Chapter 8.",
        "contexts": [
          "... and it brings no small gains unto you. Hence you wire-draw his cathedral infallibility, legislative authorit ..."
        ]
      },
      {
        "target": "Vice-Deus",
        "description": "Capitalized hyphenation with unrecognized right particle",
        "chapter": "Chapter 8.",
        "contexts": [
          "... e Vicar of Christ, Head and Spouse of his Church, Vice-Deus, Deus alter in Terris,\" and the like, whereby you ..."
        ]
      },
      {
        "target": "un-acquaintedness",
        "description": "Splittable word (rejoins to valid word 'unacquaintedness')",
        "chapter": "Chapter 11.",
        "contexts": [
          "... larly your assertions and inferences, or, through un-acquaintedness with the stories of some things that you referred ..."
        ]
      },
      {
        "target": "un-impeached",
        "description": "Splittable word (rejoins to valid word 'unimpeached')",
        "chapter": "Chapter 12.",
        "contexts": [
          "... lst the formal reason of faith remains absolutely un-impeached, different apprehensions about particular things ..."
        ]
      },
      {
        "target": "hard-hearted",
        "description": "Splittable word (rejoins to valid word 'hardhearted')",
        "chapter": "Chapter 12.",
        "contexts": [
          "... len into somewhat an unhappy age, wherein men are hard-hearted, and will not give away their faith and reason to ..."
        ]
      },
      {
        "target": "over-confident",
        "description": "Splittable word (rejoins to valid word 'overconfident')",
        "chapter": "Chapter 13.",
        "contexts": [
          "... that you back your request with nothing but some over-confident asseverations, subscribed with \"Teste meipso,\" I ..."
        ]
      },
      {
        "target": "pre-eminences",
        "description": "Hyphenated word with unrecognized particles on both sides",
        "chapter": "Chapter 17.",
        "contexts": [
          "... of your pope, with the authority, privileges, and pre-eminences which by virtue thereof he lays claim unto, but h ..."
        ]
      },
      {
        "target": "transubstan-tiating",
        "description": "Hyphenated word with unrecognized particles on both sides",
        "chapter": "Chapter 19.",
        "contexts": [
          "... in the canon of the mass immediately ensues your transubstan-tiating consecration before the oblation itself, and so m ..."
        ]
      },
      {
        "target": "Bibliothe-carius",
        "description": "Capitalized hyphenation with unrecognized left particle",
        "chapter": "Chapter 21.",
        "contexts": [
          "... umenical or Universal Patriarch; which Anastasius Bibliothe-carius, in his dedication of his translation of the Acts ..."
        ]
      },
      {
        "target": "hear-say",
        "description": "Splittable word (rejoins to valid word 'hearsay')",
        "chapter": "Chapter 21.",
        "contexts": [
          "... es they talked of, so that they had them all upon hear-say. Acts 4:1 4. \u0391\u03bb\u03bb\u1f70, saith he, \u03bc\u03ae\u03c4\u03b9\u03c2 \u03b5\u1f34\u03c4\u1fc3 \u03c4\u03af\u03bd\u03bf\u03c2 \u1f15\u03bd ..."
        ]
      },
      {
        "target": "Minu-tius",
        "description": "Capitalized hyphenation with unrecognized left particle",
        "chapter": "Chapter 21.",
        "contexts": [
          "... in those days heard of in the world. Arnobius or Minu-tius Felix acknowledgeth the same: \"Cruces nec colimus ..."
        ]
      },
      {
        "target": "not-withstanding",
        "description": "Splittable word (rejoins to valid word 'notwithstanding')",
        "chapter": "Chapter 21.",
        "contexts": [
          "... olten statue,\" Judges 18:Would it not, think you, not-withstanding the gaiety of all this provision, have been a mad ..."
        ]
      },
      {
        "target": "Syro-Chaldean",
        "description": "Capitalized hyphenation with unrecognized left particle",
        "chapter": "Chapter 22.",
        "contexts": [
          "... their own tongue, and most of them understood the Syro-Chaldean, wherein about that time some small parts of the ...",
          "... soon as their language began to be mixed with the Syro-Chaldean, and the purity of it to grow into disuse, made u ..."
        ]
      },
      {
        "target": "high-handed",
        "description": "Splittable word (rejoins to valid word 'highhanded')",
        "chapter": "Prefatory Note (Chapter 3 - Motive, Matter, and Method of Our Author\u00ecs Book.)",
        "contexts": [
          "... rch, and more especially with the abettors of the high-handed measures adopted by the Court for discountenancin ..."
        ]
      },
      {
        "target": "statesman-like",
        "description": "Splittable word (rejoins to valid word 'statesmanlike')",
        "chapter": "Prefatory Note (Chapter 3 - Motive, Matter, and Method of Our Author\u00ecs Book.)",
        "contexts": [
          "... e calm and nervous dignity of its reasonings; the statesman-like view it gives of the condition and prospects of t ..."
        ]
      },
      {
        "target": "birth-right",
        "description": "Splittable word (rejoins to valid word 'birthright')",
        "chapter": "The State and Fate of the Protestant Religion.",
        "contexts": [
          "... ountries, did secure unto them as a part of their birth-right inheritance. And in some places, though the name ..."
        ]
      },
      {
        "target": "re-introduction",
        "description": "Splittable word (rejoins to valid word 'reintroduction')",
        "chapter": "The State and Fate of the Protestant Religion.",
        "contexts": [
          "... s inducements, may comply with any of them in the re-introduction of Popery into any of their territories, will qui ..."
        ]
      }
    ],
    "Punctuation Spacing Blemishes": [
      {
        "target": "VI .",
        "description": "Spaced period (space before period)",
        "chapter": "Chapter 2 - Heathen Pleas - General Principles.",
        "contexts": [
          "... irect means, and entertained for sinister ends.\" VI . \"That our departure from Rome hath been the cause ..."
        ]
      },
      {
        "target": "through .",
        "description": "Spaced period (space before period)",
        "chapter": "Chapter 2 - Heathen Pleas - General Principles.",
        "contexts": [
          "... se, being converted by their means, do afterward, through .the craft and subtlety of seducers, fall in sundry ..."
        ]
      },
      {
        "target": "rule ;",
        "description": "Spaced punctuation (space before character)",
        "chapter": "Chapter 6.",
        "contexts": [
          "... eyes also. The Scripture doth its work as a moral rule ; which men are not necessitated or compelled to at ..."
        ]
      },
      {
        "target": "there ;",
        "description": "Spaced punctuation (space before character)",
        "chapter": "Chapter 8.",
        "contexts": [
          "... was at Rome; 3. That he fixed his episcopal see there ; \u2014 whereof the second is very questionable, the fi ..."
        ]
      },
      {
        "target": "Secondly ,",
        "description": "Spaced punctuation (space before character)",
        "chapter": "Chapter 16.",
        "contexts": [
          "... ove him and keep his commandments, and no other. Secondly , You may also as easily discern the frivolousness ..."
        ]
      },
      {
        "target": "10 .",
        "description": "Spaced period (space before period)",
        "chapter": "Chapter 17.",
        "contexts": [
          "... d confirmed their formerly rejected pretensions. 10 . That when they began to perceive and feel the per ..."
        ]
      }
    ],
    "OCR & Bracket Residues": [],
    "Mixed-Case Capitalization Errors": [
      {
        "target": "necLatina",
        "description": "Mixed-case capitalization error",
        "chapter": "Chapter 7.",
        "contexts": [
          "... in domiclio eogitationis, nec Hebrae, nec Graeca, necLatina, nec barbara, veritas, sine otis et linguae organ ..."
        ]
      }
    ],
    "Unresolved Citation References": [
      {
        "target": "lib. 3",
        "description": "Unresolved patristic/classical citation reference (no translation found)",
        "chapter": "To the Reader (Chapter 3 - Motive, Matter, and Method of Our Author\u00ecs Book.)",
        "contexts": [
          "... \u03b8\u03ad\u03bd\u03c4\u03b1\u03c2 \u03b5\u1fd6\u03bd\u03b1\u03b9 \u03b6\u03b5\u03af\u03bf\u03c5\u03c2 \u03bb\u03cc\u03b3\u03bf\u03c5\u03c2, \u03c4\u1f78 \u03b3\u03b5\u03bd\u03ad\u03c3\u03b8\u03b1\u03b9 \u03b1\u1f31\u03c1\u03ad\u03c3\u03b5\u03b9\u03c2, lib. 3 Con. Cel. cap. 1; \u2014 \"When many were converted unt ..."
        ]
      },
      {
        "target": "lib. 2, cap.\n\n7",
        "description": "Unresolved patristic/classical citation reference (no translation found)",
        "chapter": "Chapter 4.",
        "contexts": [
          "... ispensably he-cessary for your defense, De Idol., lib. 2, cap. 7. St Peter, he tells us, insinuates some \"worship ..."
        ]
      },
      {
        "target": "lib. 4",
        "description": "Unresolved patristic/classical citation reference (no translation found)",
        "chapter": "Chapter 12.",
        "contexts": [
          "... etter information you may do well to consult him, lib. 4 epist. 32, 36, 38; and sundry other instances may ..."
        ]
      },
      {
        "target": "epist. 32, 36, 38",
        "description": "Unresolved patristic/classical citation reference (no translation found)",
        "chapter": "Chapter 12.",
        "contexts": [
          "... nformation you may do well to consult him, lib. 4 epist. 32, 36, 38; and sundry other instances may be given out of h ..."
        ]
      },
      {
        "target": "lib. 3",
        "description": "Unresolved patristic/classical citation reference (no translation found)",
        "chapter": "Chapter 13.",
        "contexts": [
          "... ing is defended by Hosius, DeAuthoritat. Script., lib. 3, who adds unto it of his own: \"Revera nisi nos au ..."
        ]
      },
      {
        "target": "lib. 1",
        "description": "Unresolved patristic/classical citation reference (no translation found)",
        "chapter": "Chapter 21.",
        "contexts": [
          "... th the adoration of them. Theodoret. Haeret. sub. lib. 1, tells us that Simon Magus gave his own image and ...",
          "... to be worshipped by his followers. And Irenaeus, lib. 1 cap. 23, that the followers of Basilides used ima ...",
          "... they adored. And so doth Epiphanius also, tom. 2 lib. 1, Haer. 27. Carpocrates procured the images of Chr ..."
        ]
      }
    ],
    "Structural Nesting Sequence Jumps": [
      {
        "target": "V. ... VII.",
        "description": "List sequence jump (skipped from 5 to 7)",
        "chapter": "Chapter 2 - Heathen Pleas - General Principles.",
        "contexts": []
      },
      {
        "target": "3. ... 5.",
        "description": "List sequence jump (skipped from 3 to 5)",
        "chapter": "Chapter 3 - Motive, Matter, and Method of Our Author\u00ccs Book.",
        "contexts": []
      },
      {
        "target": "41.",
        "description": "List sequence starts at 41 instead of 1",
        "chapter": "Chapter 2.",
        "contexts": [
          "... hurch explained by Suarez, tom. 1 in Thom. 3, d. 41. \"A supernatural work,\" saith he, \"proceeding from ..."
        ]
      },
      {
        "target": "4.",
        "description": "List sequence starts at 4 instead of 1",
        "chapter": "Chapter 4.",
        "contexts": [
          "[[CHAPTER]] CHAPTER 4. [[SUMMARY]] Farther vindication of second chapte ...",
          "... ermines which is the heaviest, 22ae q. 94, a. ad 4. The church in the wilderness fell by its \u03bc\u03bf\u03c3\u03c7\u03bf\u03c0\u03bf\u03b9 ...",
          "... ocate only him in whom we do believe,\" Romans 10:14. It believed that the \"command to abstain from me ..."
        ]
      },
      {
        "target": "2. ... 4.",
        "description": "List sequence jump (skipped from 2 to 4)",
        "chapter": "Chapter 4.",
        "contexts": []
      },
      {
        "target": "3. ... 6.",
        "description": "List sequence jump (skipped from 3 to 6)",
        "chapter": "Chapter 4.",
        "contexts": []
      },
      {
        "target": "6. ... 381.",
        "description": "List sequence jump (skipped from 6 to 381)",
        "chapter": "Chapter 4.",
        "contexts": []
      },
      {
        "target": "4. ... 11.",
        "description": "List sequence jump (skipped from 4 to 11)",
        "chapter": "Chapter 4.",
        "contexts": []
      },
      {
        "target": "5. ... 7.",
        "description": "List sequence jump (skipped from 5 to 7)",
        "chapter": "Chapter 4.",
        "contexts": []
      },
      {
        "target": "7. ... 9.",
        "description": "List sequence jump (skipped from 7 to 9)",
        "chapter": "Chapter 4.",
        "contexts": []
      },
      {
        "target": "9. ... 754.",
        "description": "List sequence jump (skipped from 9 to 754)",
        "chapter": "Chapter 4.",
        "contexts": []
      },
      {
        "target": "6. ... 794.",
        "description": "List sequence jump (skipped from 6 to 794)",
        "chapter": "Chapter 4.",
        "contexts": []
      },
      {
        "target": "II. ... XII.",
        "description": "List sequence jump (skipped from 2 to 12)",
        "chapter": "Chapter 4.",
        "contexts": []
      },
      {
        "target": "1. ... 3.",
        "description": "List sequence jump (skipped from 1 to 3)",
        "chapter": "Chapter 8.",
        "contexts": []
      },
      {
        "target": "V. ... VII.",
        "description": "List sequence jump (skipped from 5 to 7)",
        "chapter": "Chapter 8.",
        "contexts": []
      },
      {
        "target": "1. ... 5.",
        "description": "List sequence jump (skipped from 1 to 5)",
        "chapter": "Chapter 12.",
        "contexts": []
      },
      {
        "target": "2. ... 4.",
        "description": "List sequence jump (skipped from 2 to 4)",
        "chapter": "Chapter 13.",
        "contexts": []
      },
      {
        "target": "5. ... 9.",
        "description": "List sequence jump (skipped from 5 to 9)",
        "chapter": "Chapter 13.",
        "contexts": []
      },
      {
        "target": "1. ... 4.",
        "description": "List sequence jump (skipped from 1 to 4)",
        "chapter": "Chapter 16.",
        "contexts": []
      },
      {
        "target": "III.",
        "description": "List sequence starts at 3 instead of 1",
        "chapter": "Chapter 16.",
        "contexts": [
          "... 9? and whether Queen Elizabeth, King James, Henry III. and IV. of France, had cause to believe it? and w ..."
        ]
      },
      {
        "target": "9. ... 11.",
        "description": "List sequence jump (skipped from 9 to 11)",
        "chapter": "Chapter 17.",
        "contexts": []
      },
      {
        "target": "II.",
        "description": "List sequence starts at 2 instead of 1",
        "chapter": "Chapter 17.",
        "contexts": [
          "... as did one at Rome, under Otho the emperor, John XII., a sweet bishop, anno 963; another at Sutrinum, a ...",
          "... ainst the usurpations and innovations of Gregory VII., as at Worms, Papia, Brixia, Mentz, and elsewhere ...",
          "... is with their pope's now claimed authority. Henry II. of Germany both deposed popes and limited their p ..."
        ]
      },
      {
        "target": "4. ... 490.",
        "description": "List sequence jump (skipped from 4 to 490)",
        "chapter": "Chapter 21.",
        "contexts": []
      },
      {
        "target": "2. ... 4.",
        "description": "List sequence jump (skipped from 2 to 4)",
        "chapter": "Chapter 21.",
        "contexts": []
      },
      {
        "target": "2. ... 19.",
        "description": "List sequence jump (skipped from 2 to 19)",
        "chapter": "Chapter 21.",
        "contexts": []
      },
      {
        "target": "1. ... 5.",
        "description": "List sequence jump (skipped from 1 to 5)",
        "chapter": "Chapter 21.",
        "contexts": []
      }
    ],
    "Invalid Bible References": [
      {
        "target": "Philippians 50",
        "description": "Invalid Bible reference (chapter 50 exceeds max 4 for Philippians)",
        "chapter": "Chapter 19.",
        "contexts": [
          "... \"sacrificing,\" Romans 15:16; so is faith itself, Philippians 50:17 2:17; so prayers and thanksgiving are an oblat ..."
        ]
      }
    ],
    "List Formatting Inconsistencies": []
  }
}